realtimeCanvas/__init__.py
realtimecanvas-0.1.1.dist-info/LICENSE
realtimecanvas-0.1.1.dist-info/METADATA
realtimecanvas-0.1.1.dist-info/WHEEL
realtimecanvas-0.1.1.dist-info/top_level.txt
realtimecanvas-0.1.1.dist-info/RECORD
